{
	"curve":
	[
		{
			"x": 1,
			"y": 7808
		},
		{
			"x": 7,
			"y": 15176
		},
		{
			"x": 13,
			"y": 22623
		},
		{
			"x": 19,
			"y": 30159
		},
		{
			"x": 25,
			"y": 37793
		},
		{
			"x": 31,
			"y": 45536
		},
		{
			"x": 37,
			"y": 53400
		},
		{
			"x": 43,
			"y": 61398
		},
		{
			"x": 49,
			"y": 69545
		},
		{
			"x": 55,
			"y": 77856
		},
		{
			"x": 61,
			"y": 86350
		},
		{
			"x": 67,
			"y": 95047
		},
		{
			"x": 73,
			"y": 103968
		},
		{
			"x": 79,
			"y": 113139
		},
		{
			"x": 85,
			"y": 122587
		},
		{
			"x": 91,
			"y": 132341
		},
		{
			"x": 97,
			"y": 142436
		},
		{
			"x": 103,
			"y": 152908
		},
		{
			"x": 109,
			"y": 163799
		},
		{
			"x": 115,
			"y": 175154
		},
		{
			"x": 121,
			"y": 187024
		},
		{
			"x": 127,
			"y": 199465
		},
		{
			"x": 133,
			"y": 212539
		},
		{
			"x": 139,
			"y": 226316
		},
		{
			"x": 145,
			"y": 240873
		},
		{
			"x": 151,
			"y": 256293
		},
		{
			"x": 157,
			"y": 272673
		},
		{
			"x": 163,
			"y": 290115
		},
		{
			"x": 169,
			"y": 308737
		},
		{
			"x": 175,
			"y": 328667
		},
		{
			"x": 181,
			"y": 350048
		},
		{
			"x": 187,
			"y": 373037
		},
		{
			"x": 193,
			"y": 397811
		},
		{
			"x": 199,
			"y": 424565
		},
		{
			"x": 205,
			"y": 453513
		},
		{
			"x": 211,
			"y": 484897
		},
		{
			"x": 217,
			"y": 518982
		},
		{
			"x": 223,
			"y": 556061
		},
		{
			"x": 229,
			"y": 596463
		},
		{
			"x": 235,
			"y": 640550
		},
		{
			"x": 241,
			"y": 688724
		},
		{
			"x": 247,
			"y": 741431
		},
		{
			"x": 253,
			"y": 799165
		},
		{
			"x": 259,
			"y": 862475
		},
		{
			"x": 265,
			"y": 931971
		},
		{
			"x": 271,
			"y": 1008325
		},
		{
			"x": 277,
			"y": 1092289
		},
		{
			"x": 283,
			"y": 1184690
		},
		{
			"x": 289,
			"y": 1286451
		},
		{
			"x": 295,
			"y": 1398593
		}
	]
}
