{
	"curve":
	[
		{
			"x": 1,
			"y": 118
		},
		{
			"x": 7,
			"y": 153
		},
		{
			"x": 13,
			"y": 188
		},
		{
			"x": 19,
			"y": 223
		},
		{
			"x": 25,
			"y": 258
		},
		{
			"x": 31,
			"y": 293
		},
		{
			"x": 37,
			"y": 328
		},
		{
			"x": 43,
			"y": 363
		},
		{
			"x": 49,
			"y": 398
		},
		{
			"x": 55,
			"y": 433
		},
		{
			"x": 61,
			"y": 468
		},
		{
			"x": 67,
			"y": 503
		},
		{
			"x": 73,
			"y": 538
		},
		{
			"x": 79,
			"y": 573
		},
		{
			"x": 85,
			"y": 608
		},
		{
			"x": 91,
			"y": 643
		},
		{
			"x": 97,
			"y": 678
		},
		{
			"x": 103,
			"y": 713
		},
		{
			"x": 109,
			"y": 748
		},
		{
			"x": 115,
			"y": 783
		},
		{
			"x": 121,
			"y": 818
		},
		{
			"x": 127,
			"y": 853
		},
		{
			"x": 133,
			"y": 888
		},
		{
			"x": 139,
			"y": 923
		},
		{
			"x": 145,
			"y": 959
		},
		{
			"x": 151,
			"y": 994
		},
		{
			"x": 157,
			"y": 1029
		},
		{
			"x": 163,
			"y": 1064
		},
		{
			"x": 169,
			"y": 1099
		},
		{
			"x": 175,
			"y": 1134
		},
		{
			"x": 181,
			"y": 1169
		},
		{
			"x": 187,
			"y": 1204
		},
		{
			"x": 193,
			"y": 1239
		},
		{
			"x": 199,
			"y": 1274
		},
		{
			"x": 205,
			"y": 1310
		},
		{
			"x": 211,
			"y": 1345
		},
		{
			"x": 217,
			"y": 1380
		},
		{
			"x": 223,
			"y": 1415
		},
		{
			"x": 229,
			"y": 1450
		},
		{
			"x": 235,
			"y": 1485
		},
		{
			"x": 241,
			"y": 1520
		},
		{
			"x": 247,
			"y": 1556
		},
		{
			"x": 253,
			"y": 1591
		},
		{
			"x": 259,
			"y": 1626
		},
		{
			"x": 265,
			"y": 1661
		},
		{
			"x": 271,
			"y": 1696
		},
		{
			"x": 277,
			"y": 1731
		},
		{
			"x": 283,
			"y": 1767
		},
		{
			"x": 289,
			"y": 1802
		},
		{
			"x": 295,
			"y": 1837
		}
	]
}
