{
	"curve":
	[
		{
			"x": 1,
			"y": 70
		},
		{
			"x": 7,
			"y": 74
		},
		{
			"x": 13,
			"y": 79
		},
		{
			"x": 19,
			"y": 85
		},
		{
			"x": 25,
			"y": 90
		},
		{
			"x": 31,
			"y": 97
		},
		{
			"x": 37,
			"y": 103
		},
		{
			"x": 43,
			"y": 110
		},
		{
			"x": 49,
			"y": 117
		},
		{
			"x": 55,
			"y": 125
		},
		{
			"x": 61,
			"y": 133
		},
		{
			"x": 67,
			"y": 142
		},
		{
			"x": 73,
			"y": 152
		},
		{
			"x": 79,
			"y": 162
		},
		{
			"x": 85,
			"y": 173
		},
		{
			"x": 91,
			"y": 184
		},
		{
			"x": 97,
			"y": 197
		},
		{
			"x": 103,
			"y": 210
		},
		{
			"x": 109,
			"y": 224
		},
		{
			"x": 115,
			"y": 238
		},
		{
			"x": 121,
			"y": 254
		},
		{
			"x": 127,
			"y": 271
		},
		{
			"x": 133,
			"y": 289
		},
		{
			"x": 139,
			"y": 309
		},
		{
			"x": 145,
			"y": 329
		},
		{
			"x": 151,
			"y": 351
		},
		{
			"x": 157,
			"y": 374
		},
		{
			"x": 163,
			"y": 399
		},
		{
			"x": 169,
			"y": 426
		},
		{
			"x": 175,
			"y": 454
		},
		{
			"x": 181,
			"y": 485
		},
		{
			"x": 187,
			"y": 517
		},
		{
			"x": 193,
			"y": 551
		},
		{
			"x": 199,
			"y": 588
		},
		{
			"x": 205,
			"y": 627
		},
		{
			"x": 211,
			"y": 669
		},
		{
			"x": 217,
			"y": 713
		},
		{
			"x": 223,
			"y": 761
		},
		{
			"x": 229,
			"y": 811
		},
		{
			"x": 235,
			"y": 865
		},
		{
			"x": 241,
			"y": 923
		},
		{
			"x": 247,
			"y": 984
		},
		{
			"x": 253,
			"y": 1050
		},
		{
			"x": 259,
			"y": 1120
		},
		{
			"x": 265,
			"y": 1194
		},
		{
			"x": 271,
			"y": 1274
		},
		{
			"x": 277,
			"y": 1359
		},
		{
			"x": 283,
			"y": 1449
		},
		{
			"x": 289,
			"y": 1546
		},
		{
			"x": 295,
			"y": 1648
		}
	]
}
